frequency/__init__.py
frequency/_version.py
frequency-0.0.1rc0.dist-info/METADATA
frequency-0.0.1rc0.dist-info/WHEEL
frequency-0.0.1rc0.dist-info/licenses/LICENSE
frequency-0.0.1rc0.dist-info/RECORD
